pitble
