Metadata-Version: 1.1
Name: pitble
Version: 0.0.2
Summary: Django microblog
Home-page: https://github.com/openwebinars-django/pitble/
Author: Pablo Martin, Raul Sanchez, Alberto Vara
Author-email: goinnn@gmail.com
License: LGPL 3
Keywords: django,microblog,pitble
Platform: UNKNOWN
Classifier: Development Status :: 4 - Beta
Classifier: Framework :: Django
Classifier: License :: OSI Approved :: GNU Library or Lesser General Public License (LGPL)
Classifier: Programming Language :: Python :: 2
Classifier: Programming Language :: Python :: 3
